{
  "id": "12216",
  "trade_id": "72216",
  "symbol": "EUR_JPY",
  "direction": "Long",
  "timeframe": "intraday",
  "status": "CLOSED",
  "type": "LIMIT_ORDER",
  "entry": 162.51,
  "exit": 162.62,
  "stop_loss": 161.98,
  "take_profit": 163.071,
  "quantity": 3000,
  "profit": 9.3768,
  "created": "2026-02-21T13:10:00Z",
  "closed": "2026-02-21T16:40:00Z",
  "duration_mins": 210,
  "alert_id": 441,
  "risk_reward": 2.3,
  "candles": [
    {
      "t": "2026-02-21T09:40:00Z",
      "o": 162.401,
      "h": 162.419,
      "l": 162.366,
      "c": 162.39
    },
    {
      "t": "2026-02-21T09:55:00Z",
      "o": 162.39,
      "h": 162.409,
      "l": 162.335,
      "c": 162.345
    },
    {
      "t": "2026-02-21T10:10:00Z",
      "o": 162.345,
      "h": 162.457,
      "l": 162.316,
      "c": 162.354
    },
    {
      "t": "2026-02-21T10:25:00Z",
      "o": 162.354,
      "h": 162.436,
      "l": 162.332,
      "c": 162.379
    },
    {
      "t": "2026-02-21T10:40:00Z",
      "o": 162.379,
      "h": 162.386,
      "l": 162.343,
      "c": 162.366
    },
    {
      "t": "2026-02-21T10:55:00Z",
      "o": 162.366,
      "h": 162.369,
      "l": 162.32,
      "c": 162.334
    },
    {
      "t": "2026-02-21T11:10:00Z",
      "o": 162.334,
      "h": 162.367,
      "l": 162.312,
      "c": 162.353
    },
    {
      "t": "2026-02-21T11:25:00Z",
      "o": 162.353,
      "h": 162.379,
      "l": 162.338,
      "c": 162.371
    },
    {
      "t": "2026-02-21T11:40:00Z",
      "o": 162.371,
      "h": 162.429,
      "l": 162.329,
      "c": 162.416
    },
    {
      "t": "2026-02-21T11:55:00Z",
      "o": 162.416,
      "h": 162.449,
      "l": 162.385,
      "c": 162.388
    },
    {
      "t": "2026-02-21T12:10:00Z",
      "o": 162.388,
      "h": 162.424,
      "l": 162.361,
      "c": 162.406
    },
    {
      "t": "2026-02-21T12:25:00Z",
      "o": 162.406,
      "h": 162.465,
      "l": 162.396,
      "c": 162.436
    },
    {
      "t": "2026-02-21T12:40:00Z",
      "o": 162.436,
      "h": 162.471,
      "l": 162.388,
      "c": 162.393
    },
    {
      "t": "2026-02-21T12:55:00Z",
      "o": 162.393,
      "h": 162.425,
      "l": 162.353,
      "c": 162.358
    },
    {
      "t": "2026-02-21T13:10:00Z",
      "o": 162.358,
      "h": 162.393,
      "l": 162.305,
      "c": 162.391
    },
    {
      "t": "2026-02-21T13:25:00Z",
      "o": 162.391,
      "h": 162.461,
      "l": 162.364,
      "c": 162.406
    },
    {
      "t": "2026-02-21T13:40:00Z",
      "o": 162.406,
      "h": 162.47,
      "l": 162.404,
      "c": 162.404
    },
    {
      "t": "2026-02-21T13:55:00Z",
      "o": 162.404,
      "h": 162.44,
      "l": 162.362,
      "c": 162.396
    },
    {
      "t": "2026-02-21T14:10:00Z",
      "o": 162.396,
      "h": 162.467,
      "l": 162.346,
      "c": 162.36
    },
    {
      "t": "2026-02-21T14:25:00Z",
      "o": 162.36,
      "h": 162.421,
      "l": 162.317,
      "c": 162.337
    },
    {
      "t": "2026-02-21T14:40:00Z",
      "o": 162.337,
      "h": 162.415,
      "l": 162.305,
      "c": 162.376
    },
    {
      "t": "2026-02-21T14:55:00Z",
      "o": 162.376,
      "h": 162.393,
      "l": 162.325,
      "c": 162.389
    },
    {
      "t": "2026-02-21T15:10:00Z",
      "o": 162.389,
      "h": 162.421,
      "l": 162.303,
      "c": 162.381
    },
    {
      "t": "2026-02-21T15:25:00Z",
      "o": 162.381,
      "h": 162.437,
      "l": 162.367,
      "c": 162.409
    },
    {
      "t": "2026-02-21T15:40:00Z",
      "o": 162.409,
      "h": 162.475,
      "l": 162.395,
      "c": 162.415
    },
    {
      "t": "2026-02-21T15:55:00Z",
      "o": 162.415,
      "h": 162.46,
      "l": 162.379,
      "c": 162.426
    },
    {
      "t": "2026-02-21T16:10:00Z",
      "o": 162.426,
      "h": 162.478,
      "l": 162.375,
      "c": 162.388
    },
    {
      "t": "2026-02-21T16:25:00Z",
      "o": 162.388,
      "h": 162.424,
      "l": 162.342,
      "c": 162.344
    },
    {
      "t": "2026-02-21T16:40:00Z",
      "o": 162.344,
      "h": 162.345,
      "l": 162.317,
      "c": 162.343
    },
    {
      "t": "2026-02-21T16:55:00Z",
      "o": 162.343,
      "h": 162.395,
      "l": 162.287,
      "c": 162.303
    }
  ],
  "score": {
    "trend_score": 78.5,
    "ma_score": 56.7,
    "crossover_score": 68.4,
    "oscillator_score": 68.1,
    "volatility_score": 51.6,
    "volume_score": 57.0,
    "fib_stack_score": 68.5,
    "momentum_projection_score": 66.6,
    "structure_score": 52.4,
    "cycle_score": 60.3,
    "pattern_score": 48.8,
    "final_score": 61.5,
    "confidence": 0.77,
    "entry_price": 162.51,
    "stop_price": 161.98,
    "tp_price": 163.071,
    "risk_reward": 2.0,
    "recommendation": "Buy"
  }
}