{
  "id": "3306",
  "trade_id": "3307",
  "symbol": "EUR_JPY",
  "direction": "Long",
  "timeframe": "scalp",
  "status": "CLOSED",
  "type": "LIMIT_ORDER",
  "entry": 183.141,
  "stop_loss": 183.045,
  "take_profit": 183.748,
  "quantity": 36,
  "profit": 0,
  "created": "2026-03-03T23:17:10.890346956Z",
  "closed": "2026-03-04T00:08:07Z",
  "duration_mins": 50,
  "alert_id": 3769,
  "risk_reward": 6.32291666666642,
  "candles": [
    {
      "t": "2026-03-03T23:08:00Z",
      "o": 183.03,
      "h": 183.06,
      "l": 183.017,
      "c": 183.035
    },
    {
      "t": "2026-03-03T23:09:00Z",
      "o": 183.035,
      "h": 183.05,
      "l": 183.02,
      "c": 183.027
    },
    {
      "t": "2026-03-03T23:10:00Z",
      "o": 183.035,
      "h": 183.05,
      "l": 183.016,
      "c": 183.033
    },
    {
      "t": "2026-03-03T23:11:00Z",
      "o": 183.033,
      "h": 183.063,
      "l": 183.026,
      "c": 183.06
    },
    {
      "t": "2026-03-03T23:12:00Z",
      "o": 183.057,
      "h": 183.078,
      "l": 183.048,
      "c": 183.076
    },
    {
      "t": "2026-03-03T23:13:00Z",
      "o": 183.073,
      "h": 183.09,
      "l": 183.069,
      "c": 183.069
    },
    {
      "t": "2026-03-03T23:14:00Z",
      "o": 183.076,
      "h": 183.076,
      "l": 183.044,
      "c": 183.057
    },
    {
      "t": "2026-03-03T23:15:00Z",
      "o": 183.057,
      "h": 183.08,
      "l": 183.049,
      "c": 183.059
    },
    {
      "t": "2026-03-03T23:16:00Z",
      "o": 183.063,
      "h": 183.087,
      "l": 183.046,
      "c": 183.07
    },
    {
      "t": "2026-03-03T23:17:00Z",
      "o": 183.087,
      "h": 183.09,
      "l": 183.06,
      "c": 183.065
    },
    {
      "t": "2026-03-03T23:18:00Z",
      "o": 183.069,
      "h": 183.08,
      "l": 183.058,
      "c": 183.073
    },
    {
      "t": "2026-03-03T23:19:00Z",
      "o": 183.075,
      "h": 183.113,
      "l": 183.058,
      "c": 183.109
    },
    {
      "t": "2026-03-03T23:20:00Z",
      "o": 183.103,
      "h": 183.138,
      "l": 183.09,
      "c": 183.136
    },
    {
      "t": "2026-03-03T23:21:00Z",
      "o": 183.135,
      "h": 183.15,
      "l": 183.12,
      "c": 183.135
    },
    {
      "t": "2026-03-03T23:22:00Z",
      "o": 183.134,
      "h": 183.135,
      "l": 183.1,
      "c": 183.113
    },
    {
      "t": "2026-03-03T23:23:00Z",
      "o": 183.112,
      "h": 183.134,
      "l": 183.1,
      "c": 183.122
    },
    {
      "t": "2026-03-03T23:24:00Z",
      "o": 183.124,
      "h": 183.154,
      "l": 183.1,
      "c": 183.131
    },
    {
      "t": "2026-03-03T23:25:00Z",
      "o": 183.134,
      "h": 183.14,
      "l": 183.12,
      "c": 183.123
    },
    {
      "t": "2026-03-03T23:26:00Z",
      "o": 183.127,
      "h": 183.13,
      "l": 183.108,
      "c": 183.121
    },
    {
      "t": "2026-03-03T23:27:00Z",
      "o": 183.12,
      "h": 183.14,
      "l": 183.11,
      "c": 183.123
    },
    {
      "t": "2026-03-03T23:28:00Z",
      "o": 183.118,
      "h": 183.13,
      "l": 183.109,
      "c": 183.121
    },
    {
      "t": "2026-03-03T23:29:00Z",
      "o": 183.122,
      "h": 183.13,
      "l": 183.105,
      "c": 183.11
    },
    {
      "t": "2026-03-03T23:30:00Z",
      "o": 183.11,
      "h": 183.116,
      "l": 183.09,
      "c": 183.103
    },
    {
      "t": "2026-03-03T23:31:00Z",
      "o": 183.107,
      "h": 183.124,
      "l": 183.09,
      "c": 183.1
    },
    {
      "t": "2026-03-03T23:32:00Z",
      "o": 183.122,
      "h": 183.142,
      "l": 183.1,
      "c": 183.13
    },
    {
      "t": "2026-03-03T23:33:00Z",
      "o": 183.13,
      "h": 183.14,
      "l": 183.11,
      "c": 183.137
    },
    {
      "t": "2026-03-03T23:34:00Z",
      "o": 183.136,
      "h": 183.171,
      "l": 183.12,
      "c": 183.144
    },
    {
      "t": "2026-03-03T23:35:00Z",
      "o": 183.146,
      "h": 183.15,
      "l": 183.12,
      "c": 183.142
    },
    {
      "t": "2026-03-03T23:36:00Z",
      "o": 183.144,
      "h": 183.154,
      "l": 183.12,
      "c": 183.15
    },
    {
      "t": "2026-03-03T23:37:00Z",
      "o": 183.145,
      "h": 183.16,
      "l": 183.13,
      "c": 183.144
    },
    {
      "t": "2026-03-03T23:38:00Z",
      "o": 183.145,
      "h": 183.153,
      "l": 183.13,
      "c": 183.144
    },
    {
      "t": "2026-03-03T23:39:00Z",
      "o": 183.145,
      "h": 183.149,
      "l": 183.12,
      "c": 183.131
    },
    {
      "t": "2026-03-03T23:40:00Z",
      "o": 183.13,
      "h": 183.133,
      "l": 183.11,
      "c": 183.13
    },
    {
      "t": "2026-03-03T23:41:00Z",
      "o": 183.132,
      "h": 183.144,
      "l": 183.11,
      "c": 183.129
    },
    {
      "t": "2026-03-03T23:42:00Z",
      "o": 183.128,
      "h": 183.131,
      "l": 183.1,
      "c": 183.119
    },
    {
      "t": "2026-03-03T23:43:00Z",
      "o": 183.119,
      "h": 183.163,
      "l": 183.11,
      "c": 183.143
    },
    {
      "t": "2026-03-03T23:44:00Z",
      "o": 183.145,
      "h": 183.151,
      "l": 183.12,
      "c": 183.128
    },
    {
      "t": "2026-03-03T23:45:00Z",
      "o": 183.127,
      "h": 183.142,
      "l": 183.096,
      "c": 183.134
    },
    {
      "t": "2026-03-03T23:46:00Z",
      "o": 183.136,
      "h": 183.149,
      "l": 183.1,
      "c": 183.144
    },
    {
      "t": "2026-03-03T23:47:00Z",
      "o": 183.145,
      "h": 183.159,
      "l": 183.12,
      "c": 183.155
    },
    {
      "t": "2026-03-03T23:48:00Z",
      "o": 183.14,
      "h": 183.157,
      "l": 183.12,
      "c": 183.147
    },
    {
      "t": "2026-03-03T23:49:00Z",
      "o": 183.147,
      "h": 183.165,
      "l": 183.12,
      "c": 183.163
    },
    {
      "t": "2026-03-03T23:50:00Z",
      "o": 183.165,
      "h": 183.189,
      "l": 183.16,
      "c": 183.188
    },
    {
      "t": "2026-03-03T23:51:00Z",
      "o": 183.187,
      "h": 183.187,
      "l": 183.15,
      "c": 183.169
    },
    {
      "t": "2026-03-03T23:52:00Z",
      "o": 183.167,
      "h": 183.19,
      "l": 183.15,
      "c": 183.183
    },
    {
      "t": "2026-03-03T23:53:00Z",
      "o": 183.18,
      "h": 183.189,
      "l": 183.15,
      "c": 183.17
    },
    {
      "t": "2026-03-03T23:54:00Z",
      "o": 183.171,
      "h": 183.185,
      "l": 183.16,
      "c": 183.182
    },
    {
      "t": "2026-03-03T23:55:00Z",
      "o": 183.184,
      "h": 183.192,
      "l": 183.17,
      "c": 183.191
    },
    {
      "t": "2026-03-03T23:56:00Z",
      "o": 183.189,
      "h": 183.197,
      "l": 183.17,
      "c": 183.176
    },
    {
      "t": "2026-03-03T23:57:00Z",
      "o": 183.175,
      "h": 183.21,
      "l": 183.15,
      "c": 183.195
    },
    {
      "t": "2026-03-03T23:58:00Z",
      "o": 183.194,
      "h": 183.22,
      "l": 183.17,
      "c": 183.202
    }
  ]
}