{
  "id": "12176",
  "trade_id": "72176",
  "symbol": "GBP_USD",
  "direction": "Long",
  "timeframe": "swing",
  "status": "CLOSED",
  "type": "MARKET_ORDER",
  "entry": 1.26533,
  "exit": 1.26661,
  "stop_loss": 1.25868,
  "take_profit": 1.27543,
  "quantity": 1000,
  "profit": 0,
  "created": "2026-02-14T14:09:00Z",
  "closed": "2026-02-14T14:16:00Z",
  "duration_mins": 7,
  "alert_id": 466,
  "risk_reward": 1.2,
  "candles": [
    {
      "t": "2026-02-07T14:09:00Z",
      "o": 1.26357,
      "h": 1.26475,
      "l": 1.2626,
      "c": 1.26378
    },
    {
      "t": "2026-02-08T14:09:00Z",
      "o": 1.26378,
      "h": 1.26393,
      "l": 1.26354,
      "c": 1.26369
    },
    {
      "t": "2026-02-09T14:09:00Z",
      "o": 1.26369,
      "h": 1.2641,
      "l": 1.26366,
      "c": 1.26392
    },
    {
      "t": "2026-02-10T14:09:00Z",
      "o": 1.26392,
      "h": 1.26467,
      "l": 1.26343,
      "c": 1.26344
    },
    {
      "t": "2026-02-11T14:09:00Z",
      "o": 1.26344,
      "h": 1.26385,
      "l": 1.26336,
      "c": 1.26338
    },
    {
      "t": "2026-02-12T14:09:00Z",
      "o": 1.26338,
      "h": 1.26346,
      "l": 1.26324,
      "c": 1.2634
    },
    {
      "t": "2026-02-13T14:09:00Z",
      "o": 1.2634,
      "h": 1.26359,
      "l": 1.2628,
      "c": 1.26357
    },
    {
      "t": "2026-02-14T14:09:00Z",
      "o": 1.26357,
      "h": 1.26395,
      "l": 1.26352,
      "c": 1.26366
    },
    {
      "t": "2026-02-15T14:09:00Z",
      "o": 1.26366,
      "h": 1.26398,
      "l": 1.26347,
      "c": 1.26398
    },
    {
      "t": "2026-02-16T14:09:00Z",
      "o": 1.26398,
      "h": 1.26444,
      "l": 1.26345,
      "c": 1.26425
    }
  ],
  "score": {
    "trend_score": 34.3,
    "ma_score": 37.2,
    "crossover_score": 41.3,
    "oscillator_score": 48.1,
    "volatility_score": 61.0,
    "volume_score": 47.3,
    "fib_stack_score": 35.3,
    "momentum_projection_score": 26.1,
    "structure_score": 46.4,
    "cycle_score": 49.4,
    "pattern_score": 56.9,
    "final_score": 43.9,
    "confidence": 0.48,
    "entry_price": 1.26533,
    "stop_price": 1.25868,
    "tp_price": 1.27543,
    "risk_reward": 2.0,
    "recommendation": "Sell"
  }
}