{
  "id": "2303",
  "symbol": "AUD_CHF",
  "direction": "Long",
  "timeframe": "scalp",
  "status": "CLOSED",
  "type": "LIMIT_ORDER",
  "entry": 0.55364,
  "exit": 0.5526725,
  "stop_loss": 0.55288,
  "take_profit": 0.55571,
  "quantity": 200,
  "profit": -0.1935,
  "created": "2026-03-02T23:05:52.862239601Z",
  "closed": "2026-03-02T23:09:04Z",
  "duration_mins": 3,
  "alert_id": 747,
  "risk_reward": 2.7236842105263985,
  "candles": [
    {
      "t": "2026-03-02T22:56:00Z",
      "o": 0.55255,
      "h": 0.553367,
      "l": 0.55245,
      "c": 0.553296
    },
    {
      "t": "2026-03-02T22:57:00Z",
      "o": 0.553101,
      "h": 0.55336,
      "l": 0.55253,
      "c": 0.55278
    },
    {
      "t": "2026-03-02T22:58:00Z",
      "o": 0.553195,
      "h": 0.55341,
      "l": 0.55237,
      "c": 0.553367
    },
    {
      "t": "2026-03-02T22:59:00Z",
      "o": 0.5528,
      "h": 0.553359,
      "l": 0.55231,
      "c": 0.55282
    },
    {
      "t": "2026-03-02T23:00:00Z",
      "o": 0.55281,
      "h": 0.553422,
      "l": 0.55263,
      "c": 0.55285
    },
    {
      "t": "2026-03-02T23:01:00Z",
      "o": 0.553224,
      "h": 0.553414,
      "l": 0.55261,
      "c": 0.55282
    },
    {
      "t": "2026-03-02T23:02:00Z",
      "o": 0.55262,
      "h": 0.553241,
      "l": 0.5525,
      "c": 0.553209
    },
    {
      "t": "2026-03-02T23:03:00Z",
      "o": 0.55267,
      "h": 0.553225,
      "l": 0.55264,
      "c": 0.553217
    },
    {
      "t": "2026-03-02T23:04:00Z",
      "o": 0.553225,
      "h": 0.553365,
      "l": 0.5526,
      "c": 0.55305
    },
    {
      "t": "2026-03-02T23:05:00Z",
      "o": 0.55314,
      "h": 0.553459,
      "l": 0.5527,
      "c": 0.553292
    },
    {
      "t": "2026-03-02T23:06:00Z",
      "o": 0.5532,
      "h": 0.553419,
      "l": 0.5527,
      "c": 0.55325
    },
    {
      "t": "2026-03-02T23:07:00Z",
      "o": 0.553291,
      "h": 0.5535,
      "l": 0.5528,
      "c": 0.553403
    },
    {
      "t": "2026-03-02T23:08:00Z",
      "o": 0.55324,
      "h": 0.553372,
      "l": 0.5527,
      "c": 0.5527
    },
    {
      "t": "2026-03-02T23:09:00Z",
      "o": 0.55299,
      "h": 0.553138,
      "l": 0.5525,
      "c": 0.5527
    }
  ],
  "versions": {
    "finmon": {
      "sha": "e1c282cc2512b790ef0e665ea30643ae6ef83f1b",
      "message": "Regenerate trade files missing version data"
    },
    "massive-market": {
      "sha": "8f4fcb83fbde672285f0fd7a2c68938fbced0fef",
      "message": "Update swizzley-common vendor (LoadAllVersionsMap)"
    },
    "swizzley-trader": {
      "sha": "8a785c2cdca1c1040091c5936078e6d8853a75fb",
      "message": "Update swizzley-common vendor: parseTime=true in DSN"
    }
  }
}