{
  "id": "12163",
  "trade_id": "72163",
  "symbol": "AUD_USD",
  "direction": "Short",
  "timeframe": "swing",
  "status": "CLOSED",
  "type": "MARKET_ORDER",
  "entry": 0.65134,
  "exit": 0.65206,
  "stop_loss": 0.65393,
  "take_profit": 0.64264,
  "quantity": -1000,
  "profit": -4.1049,
  "created": "2026-02-13T09:10:00Z",
  "closed": "2026-02-13T09:25:00Z",
  "duration_mins": 15,
  "alert_id": 484,
  "risk_reward": 1.0,
  "candles": [
    {
      "t": "2026-02-06T09:10:00Z",
      "o": 0.65081,
      "h": 0.65138,
      "l": 0.6507,
      "c": 0.65112
    },
    {
      "t": "2026-02-07T09:10:00Z",
      "o": 0.65112,
      "h": 0.65148,
      "l": 0.6508,
      "c": 0.65146
    },
    {
      "t": "2026-02-08T09:10:00Z",
      "o": 0.65146,
      "h": 0.65195,
      "l": 0.65072,
      "c": 0.65194
    },
    {
      "t": "2026-02-09T09:10:00Z",
      "o": 0.65194,
      "h": 0.65281,
      "l": 0.65088,
      "c": 0.65213
    },
    {
      "t": "2026-02-10T09:10:00Z",
      "o": 0.65213,
      "h": 0.65252,
      "l": 0.65174,
      "c": 0.65235
    },
    {
      "t": "2026-02-11T09:10:00Z",
      "o": 0.65235,
      "h": 0.65274,
      "l": 0.6521,
      "c": 0.65263
    },
    {
      "t": "2026-02-12T09:10:00Z",
      "o": 0.65263,
      "h": 0.65289,
      "l": 0.65214,
      "c": 0.65248
    },
    {
      "t": "2026-02-13T09:10:00Z",
      "o": 0.65248,
      "h": 0.65291,
      "l": 0.65205,
      "c": 0.65214
    },
    {
      "t": "2026-02-14T09:10:00Z",
      "o": 0.65214,
      "h": 0.65315,
      "l": 0.65164,
      "c": 0.6518
    },
    {
      "t": "2026-02-15T09:10:00Z",
      "o": 0.6518,
      "h": 0.65265,
      "l": 0.65097,
      "c": 0.65138
    }
  ],
  "score": {
    "trend_score": 41.1,
    "ma_score": 34.7,
    "crossover_score": 41.7,
    "oscillator_score": 43.3,
    "volatility_score": 60.0,
    "volume_score": 38.2,
    "fib_stack_score": 43.4,
    "momentum_projection_score": 35.6,
    "structure_score": 46.5,
    "cycle_score": 44.4,
    "pattern_score": 51.5,
    "final_score": 43.7,
    "confidence": 0.52,
    "entry_price": 0.65134,
    "stop_price": 0.65393,
    "tp_price": 0.64264,
    "risk_reward": 2.0,
    "recommendation": "Sell"
  }
}