{
  "id": "3832",
  "trade_id": "3833",
  "symbol": "USD_DKK",
  "direction": "Long",
  "timeframe": "scalp",
  "status": "CLOSED",
  "type": "LIMIT_ORDER",
  "entry": 6.44387,
  "exit": 6.4438394444444445,
  "stop_loss": 6.44176,
  "take_profit": 6.44918,
  "quantity": 36,
  "profit": -0.0011,
  "created": "2026-03-04T04:46:09.938031198Z",
  "closed": "2026-03-04T04:56:13Z",
  "duration_mins": 10,
  "alert_id": 4187,
  "risk_reward": 2.516587677724911,
  "candles": [
    {
      "t": "2026-03-04T04:37:00Z",
      "o": 6.43941,
      "h": 6.44166,
      "l": 6.4394,
      "c": 6.44028
    },
    {
      "t": "2026-03-04T04:38:00Z",
      "o": 6.44143,
      "h": 6.44182,
      "l": 6.44,
      "c": 6.44
    },
    {
      "t": "2026-03-04T04:39:00Z",
      "o": 6.44112,
      "h": 6.44128,
      "l": 6.43991,
      "c": 6.43998
    },
    {
      "t": "2026-03-04T04:40:00Z",
      "o": 6.43998,
      "h": 6.44288,
      "l": 6.4399,
      "c": 6.44185
    },
    {
      "t": "2026-03-04T04:41:00Z",
      "o": 6.44195,
      "h": 6.44315,
      "l": 6.44122,
      "c": 6.4414
    },
    {
      "t": "2026-03-04T04:42:00Z",
      "o": 6.4414,
      "h": 6.44283,
      "l": 6.44086,
      "c": 6.44282
    },
    {
      "t": "2026-03-04T04:43:00Z",
      "o": 6.44163,
      "h": 6.44273,
      "l": 6.44083,
      "c": 6.44169
    },
    {
      "t": "2026-03-04T04:44:00Z",
      "o": 6.44203,
      "h": 6.4427,
      "l": 6.44062,
      "c": 6.44109
    },
    {
      "t": "2026-03-04T04:45:00Z",
      "o": 6.44204,
      "h": 6.44275,
      "l": 6.44082,
      "c": 6.4422
    },
    {
      "t": "2026-03-04T04:46:00Z",
      "o": 6.4425,
      "h": 6.44262,
      "l": 6.44063,
      "c": 6.44068
    },
    {
      "t": "2026-03-04T04:47:00Z",
      "o": 6.44182,
      "h": 6.44349,
      "l": 6.44057,
      "c": 6.44235
    },
    {
      "t": "2026-03-04T04:48:00Z",
      "o": 6.44343,
      "h": 6.44345,
      "l": 6.4421,
      "c": 6.44336
    },
    {
      "t": "2026-03-04T04:49:00Z",
      "o": 6.4434,
      "h": 6.44355,
      "l": 6.44214,
      "c": 6.44218
    },
    {
      "t": "2026-03-04T04:50:00Z",
      "o": 6.4421,
      "h": 6.44392,
      "l": 6.4421,
      "c": 6.44285
    },
    {
      "t": "2026-03-04T04:51:00Z",
      "o": 6.4437,
      "h": 6.44403,
      "l": 6.44271,
      "c": 6.44282
    },
    {
      "t": "2026-03-04T04:52:00Z",
      "o": 6.4436,
      "h": 6.44588,
      "l": 6.44244,
      "c": 6.44342
    },
    {
      "t": "2026-03-04T04:53:00Z",
      "o": 6.44437,
      "h": 6.44531,
      "l": 6.44329,
      "c": 6.44397
    },
    {
      "t": "2026-03-04T04:54:00Z",
      "o": 6.44397,
      "h": 6.44499,
      "l": 6.44282,
      "c": 6.44448
    },
    {
      "t": "2026-03-04T04:55:00Z",
      "o": 6.44344,
      "h": 6.4445,
      "l": 6.44301,
      "c": 6.44338
    },
    {
      "t": "2026-03-04T04:56:00Z",
      "o": 6.44313,
      "h": 6.4445,
      "l": 6.44236,
      "c": 6.44254
    }
  ]
}