{
  "id": "5224",
  "trade_id": "5225",
  "symbol": "AUD_CHF",
  "direction": "Short",
  "timeframe": "scalp",
  "status": "CLOSED",
  "type": "LIMIT_ORDER",
  "entry": 0.54926,
  "exit": 0.55066625,
  "stop_loss": 0.55018,
  "take_profit": 0.54599,
  "quantity": -16,
  "profit": -0.0225,
  "created": "2026-03-04T12:39:13.853948964Z",
  "closed": "2026-03-04T13:11:24Z",
  "duration_mins": 32,
  "alert_id": 5066,
  "risk_reward": 3.5543478260868278,
  "candles": [
    {
      "t": "2026-03-04T12:30:00Z",
      "o": 0.549654,
      "h": 0.549777,
      "l": 0.5491,
      "c": 0.54946
    },
    {
      "t": "2026-03-04T12:31:00Z",
      "o": 0.54945,
      "h": 0.549691,
      "l": 0.5491,
      "c": 0.5492
    },
    {
      "t": "2026-03-04T12:32:00Z",
      "o": 0.5493,
      "h": 0.54948,
      "l": 0.5491,
      "c": 0.54923
    },
    {
      "t": "2026-03-04T12:33:00Z",
      "o": 0.5493,
      "h": 0.549472,
      "l": 0.5489,
      "c": 0.5491
    },
    {
      "t": "2026-03-04T12:34:00Z",
      "o": 0.549316,
      "h": 0.54962,
      "l": 0.5489,
      "c": 0.549432
    },
    {
      "t": "2026-03-04T12:35:00Z",
      "o": 0.549439,
      "h": 0.549526,
      "l": 0.5488,
      "c": 0.549479
    },
    {
      "t": "2026-03-04T12:36:00Z",
      "o": 0.5493,
      "h": 0.549768,
      "l": 0.5488,
      "c": 0.54948
    },
    {
      "t": "2026-03-04T12:37:00Z",
      "o": 0.549511,
      "h": 0.549722,
      "l": 0.5487,
      "c": 0.54945
    },
    {
      "t": "2026-03-04T12:38:00Z",
      "o": 0.54945,
      "h": 0.549737,
      "l": 0.5487,
      "c": 0.5489
    },
    {
      "t": "2026-03-04T12:39:00Z",
      "o": 0.54962,
      "h": 0.549862,
      "l": 0.5489,
      "c": 0.54972
    },
    {
      "t": "2026-03-04T12:40:00Z",
      "o": 0.54975,
      "h": 0.549886,
      "l": 0.5488,
      "c": 0.54976
    },
    {
      "t": "2026-03-04T12:41:00Z",
      "o": 0.5498,
      "h": 0.549878,
      "l": 0.5489,
      "c": 0.54981
    },
    {
      "t": "2026-03-04T12:42:00Z",
      "o": 0.54973,
      "h": 0.550026,
      "l": 0.5489,
      "c": 0.54958
    },
    {
      "t": "2026-03-04T12:43:00Z",
      "o": 0.54989,
      "h": 0.550244,
      "l": 0.5491,
      "c": 0.55012
    },
    {
      "t": "2026-03-04T12:44:00Z",
      "o": 0.550135,
      "h": 0.550276,
      "l": 0.5492,
      "c": 0.549989
    },
    {
      "t": "2026-03-04T12:45:00Z",
      "o": 0.549979,
      "h": 0.550057,
      "l": 0.5492,
      "c": 0.549729
    },
    {
      "t": "2026-03-04T12:46:00Z",
      "o": 0.54978,
      "h": 0.549964,
      "l": 0.5492,
      "c": 0.54988
    },
    {
      "t": "2026-03-04T12:47:00Z",
      "o": 0.549943,
      "h": 0.55001,
      "l": 0.5493,
      "c": 0.5495
    },
    {
      "t": "2026-03-04T12:48:00Z",
      "o": 0.54986,
      "h": 0.550252,
      "l": 0.5494,
      "c": 0.550252
    },
    {
      "t": "2026-03-04T12:49:00Z",
      "o": 0.550163,
      "h": 0.550322,
      "l": 0.5494,
      "c": 0.55018
    },
    {
      "t": "2026-03-04T12:50:00Z",
      "o": 0.55018,
      "h": 0.550377,
      "l": 0.5493,
      "c": 0.55008
    },
    {
      "t": "2026-03-04T12:51:00Z",
      "o": 0.55012,
      "h": 0.550252,
      "l": 0.5493,
      "c": 0.5495
    },
    {
      "t": "2026-03-04T12:52:00Z",
      "o": 0.55009,
      "h": 0.550205,
      "l": 0.5494,
      "c": 0.5495
    },
    {
      "t": "2026-03-04T12:53:00Z",
      "o": 0.549982,
      "h": 0.550051,
      "l": 0.5494,
      "c": 0.5494
    },
    {
      "t": "2026-03-04T12:54:00Z",
      "o": 0.5495,
      "h": 0.549932,
      "l": 0.5493,
      "c": 0.54971
    },
    {
      "t": "2026-03-04T12:55:00Z",
      "o": 0.54971,
      "h": 0.549903,
      "l": 0.5493,
      "c": 0.549741
    },
    {
      "t": "2026-03-04T12:56:00Z",
      "o": 0.549757,
      "h": 0.549925,
      "l": 0.5494,
      "c": 0.5495
    },
    {
      "t": "2026-03-04T12:57:00Z",
      "o": 0.54977,
      "h": 0.549954,
      "l": 0.5493,
      "c": 0.549871
    },
    {
      "t": "2026-03-04T12:58:00Z",
      "o": 0.549848,
      "h": 0.550051,
      "l": 0.5493,
      "c": 0.54992
    },
    {
      "t": "2026-03-04T12:59:00Z",
      "o": 0.550027,
      "h": 0.550051,
      "l": 0.5492,
      "c": 0.54988
    },
    {
      "t": "2026-03-04T13:00:00Z",
      "o": 0.54989,
      "h": 0.550214,
      "l": 0.5492,
      "c": 0.54998
    },
    {
      "t": "2026-03-04T13:01:00Z",
      "o": 0.550081,
      "h": 0.550339,
      "l": 0.5493,
      "c": 0.55012
    },
    {
      "t": "2026-03-04T13:02:00Z",
      "o": 0.550144,
      "h": 0.550386,
      "l": 0.5493,
      "c": 0.55014
    },
    {
      "t": "2026-03-04T13:03:00Z",
      "o": 0.550203,
      "h": 0.550495,
      "l": 0.5494,
      "c": 0.55025
    },
    {
      "t": "2026-03-04T13:04:00Z",
      "o": 0.550253,
      "h": 0.550659,
      "l": 0.5495,
      "c": 0.55027
    },
    {
      "t": "2026-03-04T13:05:00Z",
      "o": 0.550318,
      "h": 0.55065,
      "l": 0.5494,
      "c": 0.550407
    },
    {
      "t": "2026-03-04T13:06:00Z",
      "o": 0.550399,
      "h": 0.550681,
      "l": 0.5496,
      "c": 0.5498
    },
    {
      "t": "2026-03-04T13:07:00Z",
      "o": 0.550673,
      "h": 0.550673,
      "l": 0.5496,
      "c": 0.550382
    },
    {
      "t": "2026-03-04T13:08:00Z",
      "o": 0.55032,
      "h": 0.550649,
      "l": 0.5497,
      "c": 0.550409
    },
    {
      "t": "2026-03-04T13:09:00Z",
      "o": 0.5497,
      "h": 0.550735,
      "l": 0.5497,
      "c": 0.5498
    },
    {
      "t": "2026-03-04T13:10:00Z",
      "o": 0.55026,
      "h": 0.550602,
      "l": 0.5497,
      "c": 0.550397
    },
    {
      "t": "2026-03-04T13:11:00Z",
      "o": 0.55035,
      "h": 0.550641,
      "l": 0.5497,
      "c": 0.55036
    }
  ],
  "score": {
    "Symbol": "AUDCHF",
    "T": 1772627820000,
    "Time": "",
    "trend_score": -13,
    "ma_score": -54,
    "crossover_score": -3,
    "oscillator_score": -14,
    "volatility_score": -4,
    "volume_score": 0,
    "fib_stack_score": 1,
    "momentum_projection_score": -10,
    "structure_score": 1,
    "cycle_score": 1,
    "pattern_score": -2,
    "final_score": -21.6,
    "confidence": 0.7627,
    "entry_price": 0.54952,
    "stop_price": 0.5497,
    "tp_price": 0.54756,
    "risk_reward": 10.95,
    "unit_size": 0,
    "recommended_timeframe": "scalp",
    "recommendation": "Moderate Sell"
  },
  "versions": {
    "finmon": {
      "sha": "ecfd28607c8ec937d7fcedcaaf7ac681d98efa2b",
      "message": "Fix collectVersions by reading versions from DB instead of filesystem"
    },
    "massive-market": {
      "sha": "8f4fcb83fbde672285f0fd7a2c68938fbced0fef",
      "message": "Update swizzley-common vendor (LoadAllVersionsMap)"
    },
    "swizzley-trader": {
      "sha": "2dbf714572cfd4fb4787cf3bf6b603ca8196598a",
      "message": "Use single autoclose.scalp setting (Enabled=toggle, Value=min pips)"
    }
  }
}