{
  "date": "2026-02-24",
  "summary": {
    "total_orders": 1,
    "pending": 0,
    "open_positions": 0,
    "closed_orders": 1,
    "total_pl": -1.15,
    "winners": 0,
    "losers": 1,
    "breakeven": 0,
    "win_loss_ratio": 0,
    "win_rate_pct": 0,
    "avg_win": null,
    "avg_loss": -1.15,
    "avg_time_in_trade_mins": 720,
    "by_timeframe": [
      {
        "timeframe": "swing",
        "total_orders": 1,
        "pending": 0,
        "open_positions": 0,
        "closed_orders": 1,
        "total_pl": -1.15,
        "winners": 0,
        "losers": 1,
        "breakeven": 0,
        "win_loss_ratio": 0,
        "win_rate_pct": 0,
        "avg_win": null,
        "avg_loss": -1.15,
        "avg_time_in_trade_mins": 720
      }
    ]
  },
  "hours": [
    {
      "hour": 12,
      "summary": {
        "total_orders": 1,
        "pending": 0,
        "open_positions": 0,
        "closed_orders": 1,
        "total_pl": -1.15,
        "winners": 0,
        "losers": 1,
        "breakeven": 0,
        "win_loss_ratio": 0,
        "win_rate_pct": 0,
        "avg_win": null,
        "avg_loss": -1.15,
        "avg_time_in_trade_mins": 720
      },
      "orders": [
        {
          "id": "7",
          "symbol": "GBP_NZD",
          "direction": "Long",
          "timeframe": "swing",
          "status": "CLOSED",
          "type": "LIMIT_ORDER",
          "entry": 2.26115,
          "exit": 2.2599974,
          "stop_loss": 2.2593,
          "take_profit": 2.2673,
          "quantity": 1000,
          "profit": -1.1526,
          "created": "2026-02-24T12:30:00Z",
          "closed": "2026-02-25T00:30:54Z",
          "duration_mins": 720,
          "risk_reward": 3.3243243243240257,
          "versions": {
            "finmon": {
              "sha": "e1c282cc2512b790ef0e665ea30643ae6ef83f1b",
              "message": "Regenerate trade files missing version data"
            },
            "massive-market": {
              "sha": "8f4fcb83fbde672285f0fd7a2c68938fbced0fef",
              "message": "Update swizzley-common vendor (LoadAllVersionsMap)"
            },
            "swizzley-trader": {
              "sha": "8a785c2cdca1c1040091c5936078e6d8853a75fb",
              "message": "Update swizzley-common vendor: parseTime=true in DSN"
            }
          }
        }
      ]
    }
  ]
}